{
  "generated_at_utc": "2026-06-15T21:18:28+00:00",
  "lookback_hours": 72,
  "items": [
    {
      "title": "Banknote imagery advisory group minutes – 15 December 2025",
      "source": "Bank of England",
      "link": "https://www.bankofengland.co.uk/minutes/2025/december/banknote-advisory-minutes-15-december",
      "published_utc": "2026-06-15T09:00:00+00:00",
      "categories": [
        "financial_stability",
        "institutions"
      ]
    },
    {
      "title": "Banknote imagery expert panel minutes – 10 March 2026",
      "source": "Bank of England",
      "link": "https://www.bankofengland.co.uk/minutes/2026/march/banknote-expert-minutes-10-march",
      "published_utc": "2026-06-15T08:00:00+00:00",
      "categories": [
        "financial_stability",
        "institutions"
      ]
    },
    {
      "title": "Banknote imagery expert panel minutes – 15 April 2026",
      "source": "Bank of England",
      "link": "https://www.bankofengland.co.uk/minutes/2026/april/banknote-advisory-minutes-15-april",
      "published_utc": "2026-06-15T08:00:00+00:00",
      "categories": [
        "financial_stability",
        "institutions"
      ]
    },
    {
      "title": "Banknote imagery expert panel minutes – 24 April 2026",
      "source": "Bank of England",
      "link": "https://www.bankofengland.co.uk/minutes/2026/april/banknote-expert-minutes-24-april",
      "published_utc": "2026-06-15T08:00:00+00:00",
      "categories": [
        "financial_stability",
        "institutions"
      ]
    },
    {
      "title": "Banknote imagery advisory group minutes – 29 April 2026",
      "source": "Bank of England",
      "link": "https://www.bankofengland.co.uk/minutes/2026/april/banknote-advisory-minutes-29-april",
      "published_utc": "2026-06-15T08:00:00+00:00",
      "categories": [
        "financial_stability",
        "institutions"
      ]
    }
  ]
}